CHANGES.txt
README.txt
bootstrap.py
buildout.cfg
setup.py
src/zc/__init__.py
src/zc.comment.egg-info/PKG-INFO
src/zc.comment.egg-info/SOURCES.txt
src/zc.comment.egg-info/dependency_links.txt
src/zc.comment.egg-info/namespace_packages.txt
src/zc.comment.egg-info/not-zip-safe
src/zc.comment.egg-info/requires.txt
src/zc.comment.egg-info/top_level.txt
src/zc/comment/README.txt
src/zc/comment/__init__.py
src/zc/comment/comment.py
src/zc/comment/configure.zcml
src/zc/comment/i18n.py
src/zc/comment/interfaces.py
src/zc/comment/tests.py
src/zc/comment/browser/README.txt
src/zc/comment/browser/__init__.py
src/zc/comment/browser/comments.pt
src/zc/comment/browser/commentssub.pt
src/zc/comment/browser/configure.zcml
src/zc/comment/browser/ftesting.zcml
src/zc/comment/browser/tests.py
src/zc/comment/browser/views.py
src/zc/comment/browser/widget.py