Metadata-Version: 1.0
Name: zc.comment
Version: 0.1.0
Summary: A simple comment package.
Home-page: http://pypi.python.org/pypi/zc.comment
Author: Zope Community
Author-email: zope-dev@zope.org
License: ZPL 2.1
Keywords: zope3 comment
Platform: UNKNOWN
Classifier: Development Status :: 4 - Beta
Classifier: Environment :: Web Environment
Classifier: Intended Audience :: Developers
Classifier: License :: OSI Approved :: Zope Public License
Classifier: Programming Language :: Python
Classifier: Natural Language :: English
Classifier: Operating System :: OS Independent
Classifier: Topic :: Internet :: WWW/HTTP
Classifier: Framework :: Zope3
